oudjirasign/__init__.py
oudjirasign-0.1.dist-info/LICENSE
oudjirasign-0.1.dist-info/METADATA
oudjirasign-0.1.dist-info/WHEEL
oudjirasign-0.1.dist-info/entry_points.txt
oudjirasign-0.1.dist-info/top_level.txt
oudjirasign-0.1.dist-info/RECORD
