Metadata-Version: 2.1
Name: oudjirasign
Version: 0.1
Summary: Module python de signature electronique.
Home-page: https://github.com/oumar90/oudjirasign
Author: Oumar Djimé Ratou
Author-email: oudjira90@gmail.com
License: MIT
Platform: UNKNOWN
Classifier: Development Status :: 4 - Beta
Classifier: License :: OSI Approved :: MIT License
Classifier: Programming Language :: Python :: 3
Classifier: Programming Language :: Python :: 3.7
Requires-Dist: pycryptodome
Requires-Dist: progress
Requires-Dist: cryptography
Requires-Dist: argparse
